ida_allins.pyi
ida_api.pyi
ida_auto.pyi
ida_bitrange.pyi
ida_bytes.pyi
ida_dbg.pyi
ida_dirtree.pyi
ida_diskio.pyi
ida_entry.pyi
ida_expr.pyi
ida_fixup.pyi
ida_fpro.pyi
ida_frame.pyi
ida_funcs.pyi
ida_gdl.pyi
ida_graph.pyi
ida_hexrays.pyi
ida_ida.pyi
ida_idaapi.pyi
ida_idc.pyi
ida_idd.pyi
ida_idp.pyi
ida_ieee.pyi
ida_kernwin.pyi
ida_libfuncs.pyi
ida_lines.pyi
ida_loader.pyi
ida_merge.pyi
ida_mergemod.pyi
ida_moves.pyi
ida_nalt.pyi
ida_name.pyi
ida_netnode.pyi
ida_offset.pyi
ida_pro.pyi
ida_problems.pyi
ida_range.pyi
ida_regfinder.pyi
ida_registry.pyi
ida_search.pyi
ida_segment.pyi
ida_segregs.pyi
ida_srclang.pyi
ida_strlist.pyi
ida_tryblks.pyi
ida_typeinf.pyi
ida_ua.pyi
ida_undo.pyi
ida_xref.pyi
idaapi.pyi
idadex.pyi
idautils.pyi
idc.pyi
idapro/__init__.py
idapro/config.py
idapro/py.typed
idapro/stubs/ida_allins.pyi
idapro/stubs/ida_api.pyi
idapro/stubs/ida_auto.pyi
idapro/stubs/ida_bitrange.pyi
idapro/stubs/ida_bytes.pyi
idapro/stubs/ida_dbg.pyi
idapro/stubs/ida_dirtree.pyi
idapro/stubs/ida_diskio.pyi
idapro/stubs/ida_entry.pyi
idapro/stubs/ida_expr.pyi
idapro/stubs/ida_fixup.pyi
idapro/stubs/ida_fpro.pyi
idapro/stubs/ida_frame.pyi
idapro/stubs/ida_funcs.pyi
idapro/stubs/ida_gdl.pyi
idapro/stubs/ida_graph.pyi
idapro/stubs/ida_hexrays.pyi
idapro/stubs/ida_ida.pyi
idapro/stubs/ida_idaapi.pyi
idapro/stubs/ida_idc.pyi
idapro/stubs/ida_idd.pyi
idapro/stubs/ida_idp.pyi
idapro/stubs/ida_ieee.pyi
idapro/stubs/ida_kernwin.pyi
idapro/stubs/ida_libfuncs.pyi
idapro/stubs/ida_lines.pyi
idapro/stubs/ida_loader.pyi
idapro/stubs/ida_merge.pyi
idapro/stubs/ida_mergemod.pyi
idapro/stubs/ida_moves.pyi
idapro/stubs/ida_nalt.pyi
idapro/stubs/ida_name.pyi
idapro/stubs/ida_netnode.pyi
idapro/stubs/ida_offset.pyi
idapro/stubs/ida_pro.pyi
idapro/stubs/ida_problems.pyi
idapro/stubs/ida_range.pyi
idapro/stubs/ida_regfinder.pyi
idapro/stubs/ida_registry.pyi
idapro/stubs/ida_search.pyi
idapro/stubs/ida_segment.pyi
idapro/stubs/ida_segregs.pyi
idapro/stubs/ida_srclang.pyi
idapro-0.0.5.dist-info/licenses/LICENSE
idapro-0.0.5.dist-info/METADATA
idapro-0.0.5.dist-info/WHEEL
idapro-0.0.5.dist-info/top_level.txt
idapro-0.0.5.dist-info/RECORD
